pywfm/__init__.py
pywfm/budget.py
pywfm/cli.py
pywfm/decorators.py
pywfm/misc.py
pywfm/model.py
pywfm/utilities.py
pywfm/zbudget.py
iwfm_pywfm-0.2.5.dist-info/LICENSE
iwfm_pywfm-0.2.5.dist-info/METADATA
iwfm_pywfm-0.2.5.dist-info/WHEEL
iwfm_pywfm-0.2.5.dist-info/entry_points.txt
iwfm_pywfm-0.2.5.dist-info/top_level.txt
iwfm_pywfm-0.2.5.dist-info/RECORD
