Metadata-Version: 2.1
Name: iwfm-pywfm
Version: 0.2.5
Summary: python library to interact with Integrated Water Flow Model (IWFM) applications
Author-email: Tyler Hatch <hatch.tyler@gmail.com>
License: MIT License
Project-URL: Documentation, https://sgmomodeling.github.io/PyWFM
Project-URL: Repository, https://github.com/SGMOModeling/PyWFM
Project-URL: Issues, https://github.com/SGMOModeling/PyWFM/issues
Classifier: Programming Language :: Python :: 3
Classifier: License :: OSI Approved :: MIT License
Classifier: Operating System :: Microsoft :: Windows :: Windows 10
Classifier: Operating System :: Microsoft :: Windows :: Windows 11
License-File: LICENSE
Requires-Dist: numpy
Requires-Dist: matplotlib
Requires-Dist: pandas
Requires-Dist: Click
Requires-Dist: requests
